javis/__init__.py
javis/server.py
javis/handlers/__init__.py
javis/handlers/interface_handler.py
javis/handlers/prompt_handlers.py
javis/handlers/rag_handler.py
javis/handlers/requirement_handler.py
javis/handlers/resource_handler.py
javis/handlers/tool_handlers.py
javis/modules/__init__.py
javis/modules/config.py
javis/modules/data_models.py
javis/modules/file_utils.py
javis/modules/persistent_storage.py
javis/modules/rule_fetcher.py
javis/prompts/__init__.py
javis/prompts/prompt_templates.py
javis/rag/__init__.py
javis/rag/code_loader.py
javis/rag/leann_store.py
javis/rag/rag_service.py
javis/rag/vector_store.py
javis/rag/vector_store_factory.py
pyarmor_runtime_000000/__init__.py
pyarmor_runtime_000000/pyarmor_runtime.so
javis_agent-1.1.11.dist-info/METADATA
javis_agent-1.1.11.dist-info/WHEEL
javis_agent-1.1.11.dist-info/entry_points.txt
javis_agent-1.1.11.dist-info/RECORD
